{
  "culture": "en",
  "texts": {
    "ExternalAuthenticationProvider": "Provider",
    "ExternalAuthenticationProviders": "Providers",
    "Permission:ChangePermissions": "Change permissions",
    "Permission:ExternalAuthenticationProvider": "External Authentication Provider",
    "ExternalAuthentication.Provider.ManagePermissions": "Manage",
    "ExternalAuthentication:Provider": "Provider",
    "ExternalAuthentication:Enabled": "Enabled",
    "ExternalAuthentication:ReturnUrl": "Return Url",
    "ExternalAuthentication:ReturnUrlHash": "Return Url Hash",
    "GitHub": "GitHub",
    "Gitee": "Gitee",
    "MicrosoftAccount": "Microsoft Account",
    "NewUserPrefix": "Prefix for created external users",
    "NewUserEmailSuffix": "Email suffix for created external users"
  }
}